gitlab_har_recorder/__init__.py
gitlab_har_recorder-9.0.2.dist-info/METADATA
gitlab_har_recorder-9.0.2.dist-info/WHEEL
gitlab_har_recorder-9.0.2.dist-info/top_level.txt
gitlab_har_recorder-9.0.2.dist-info/RECORD
